timestamped_for_f1_historical_api/__init__.py
timestamped_for_f1_historical_api/api/__init__.py
timestamped_for_f1_historical_api/api/v1/__init__.py
timestamped_for_f1_historical_api/api/v1/circuit/__init__.py
timestamped_for_f1_historical_api/api/v1/circuit/models.py
timestamped_for_f1_historical_api/api/v1/circuit/services.py
timestamped_for_f1_historical_api/api/v1/circuit/views.py
timestamped_for_f1_historical_api/api/v1/country/__init__.py
timestamped_for_f1_historical_api/api/v1/country/models.py
timestamped_for_f1_historical_api/api/v1/country/services.py
timestamped_for_f1_historical_api/api/v1/driver/__init__.py
timestamped_for_f1_historical_api/api/v1/driver/models.py
timestamped_for_f1_historical_api/api/v1/driver/services.py
timestamped_for_f1_historical_api/api/v1/driver/views.py
timestamped_for_f1_historical_api/api/v1/event/__init__.py
timestamped_for_f1_historical_api/api/v1/event/enums.py
timestamped_for_f1_historical_api/api/v1/event/models.py
timestamped_for_f1_historical_api/api/v1/event/services.py
timestamped_for_f1_historical_api/api/v1/event/views.py
timestamped_for_f1_historical_api/api/v1/event_role/enums.py
timestamped_for_f1_historical_api/api/v1/event_role/models.py
timestamped_for_f1_historical_api/api/v1/event_role/services.py
timestamped_for_f1_historical_api/api/v1/location/__init__.py
timestamped_for_f1_historical_api/api/v1/location/models.py
timestamped_for_f1_historical_api/api/v1/location/services.py
timestamped_for_f1_historical_api/api/v1/meeting/__init__.py
timestamped_for_f1_historical_api/api/v1/meeting/models.py
timestamped_for_f1_historical_api/api/v1/meeting/services.py
timestamped_for_f1_historical_api/api/v1/meeting/views.py
timestamped_for_f1_historical_api/api/v1/pit/__init__.py
timestamped_for_f1_historical_api/api/v1/pit/models.py
timestamped_for_f1_historical_api/api/v1/pit/services.py
timestamped_for_f1_historical_api/api/v1/race_control/__init__.py
timestamped_for_f1_historical_api/api/v1/race_control/models.py
timestamped_for_f1_historical_api-0.1.1.dist-info/WHEEL
timestamped_for_f1_historical_api-0.1.1.dist-info/METADATA
timestamped_for_f1_historical_api-0.1.1.dist-info/RECORD
