Metadata-Version: 2.3
Name: timestamped-for-f1-historical-api
Version: 0.1.1
Author: Jeffrey Zhang
Author-email: Jeffrey Zhang <jeffreyjpizhang@gmail.com>
Requires-Dist: alembic>=1.16.2
Requires-Dist: asyncio>=3.4.3
Requires-Dist: asyncpg>=0.30.0
Requires-Dist: datetime>=5.5
Requires-Dist: fastapi[standard]>=0.116.0
Requires-Dist: pydantic-settings>=2.10.1
Requires-Dist: sqlalchemy>=2.0.41
Requires-Dist: sqlalchemy-helpers>=2.0.1
Requires-Dist: uvicorn>=0.34.3
Requires-Python: >=3.13
